changanya/__init__.py
changanya/bloom.py
changanya/geohash.py
changanya/hashtype.py
changanya/nilsimsa.py
changanya/simhash.py
changanya-0.5.0.dist-info/DESCRIPTION.rst
changanya-0.5.0.dist-info/METADATA
changanya-0.5.0.dist-info/RECORD
changanya-0.5.0.dist-info/WHEEL
changanya-0.5.0.dist-info/metadata.json
changanya-0.5.0.dist-info/top_level.txt
examples/__init__.py
examples/usage.py
